<GTFSAgencies><GTFSAgency Id="3D" Name="Tri Delta Transit" LastGenerated="10/22/2025 10:20:03 AM"/><GTFSAgency Id="AC" Name="AC Transit" LastGenerated="8/10/2025 12:28:22 AM"/><GTFSAgency Id="AF" Name="Angel Island Tiburon Ferry" LastGenerated="10/11/2025 11:00:04 AM"/><GTFSAgency Id="AM" Name="Capitol Corridor Joint Powers Authority" LastGenerated="10/5/2025 11:23:58 PM"/><GTFSAgency Id="BA" Name="Bay Area Rapid Transit" LastGenerated="10/24/2025 10:27:08 AM"/><GTFSAgency Id="CC" Name="County Connection" LastGenerated="10/6/2025 9:25:18 AM"/><GTFSAgency Id="CE" Name="Altamont Corridor Express" LastGenerated="10/10/2025 9:58:40 AM"/><GTFSAgency Id="CM" Name="Commute.org Shuttles" LastGenerated="6/23/2025 3:25:35 AM"/><GTFSAgency Id="CT" Name="Caltrain" LastGenerated="9/22/2025 6:47:05 PM"/><GTFSAgency Id="DE" Name="Dumbarton Express Consortium" LastGenerated="10/5/2025 9:02:57 PM"/><GTFSAgency Id="EE" Name="Emery Express" LastGenerated="1/30/2025 11:16:12 AM"/><GTFSAgency Id="EM" Name="Emery Go-Round" LastGenerated="1/30/2025 1:11:09 PM"/><GTFSAgency Id="FS" Name="FAST" LastGenerated="5/8/2025 2:55:57 AM"/><GTFSAgency Id="GF" Name="Golden Gate Ferry" LastGenerated="10/2/2025 3:03:14 PM"/><GTFSAgency Id="GG" Name="Golden Gate Transit" LastGenerated="10/7/2025 10:50:57 AM"/><GTFSAgency Id="GP" Name="San Francisco Recreation and Parks" LastGenerated="1/30/2025 11:18:09 AM"/><GTFSAgency Id="MA" Name="Marin Transit" LastGenerated="9/28/2025 9:15:48 PM"/><GTFSAgency Id="MB" Name="Mission Bay TMA" LastGenerated="7/10/2025 10:40:08 AM"/><GTFSAgency Id="MC" Name="Mountain View Community Shuttle" LastGenerated="8/26/2025 3:18:40 PM"/><GTFSAgency Id="MV" Name="MVgo" LastGenerated="10/14/2025 12:51:51 PM"/><GTFSAgency Id="PE" Name="PETALUMA" LastGenerated="12/30/2024 8:47:00 AM"/><GTFSAgency Id="PG" Name="Presidio Go" LastGenerated="1/8/2025 10:19:36 AM"/><GTFSAgency Id="RG" Name="Regional GTFS" LastGenerated="10/26/2025 5:42:51 AM"/><GTFSAgency Id="RV" Name="Rio Vista Delta Breeze" LastGenerated="9/22/2025 2:16:41 PM"/><GTFSAgency Id="SA" Name="Sonoma Marin Area Rail Transit" LastGenerated="10/23/2025 4:26:50 AM"/><GTFSAgency Id="SB" Name="San Francisco Bay Ferry" LastGenerated="10/17/2025 8:07:40 PM"/><GTFSAgency Id="SC" Name="VTA" LastGenerated="8/10/2025 11:16:26 PM"/><GTFSAgency Id="SF" Name="San Francisco Municipal Transportation Agency" LastGenerated="10/17/2025 7:48:32 PM"/><GTFSAgency Id="SI" Name="San Francisco International Airport" LastGenerated="5/19/2025 3:54:20 PM"/><GTFSAgency Id="SM" Name="SamTrans" LastGenerated="10/23/2025 1:09:15 PM"/><GTFSAgency Id="SO" Name="Sonoma County Transit" LastGenerated="10/8/2025 10:23:33 AM"/><GTFSAgency Id="SR" Name="SANTAROSA" LastGenerated="9/25/2025 7:48:54 AM"/><GTFSAgency Id="SS" Name="City of South San Francisco" LastGenerated="2/1/2025 6:16:24 PM"/><GTFSAgency Id="ST" Name="SolTrans" LastGenerated="10/15/2025 10:40:27 AM"/><GTFSAgency Id="TF" Name="Treasure Island Ferry" LastGenerated="1/7/2025 2:24:43 PM"/><GTFSAgency Id="UC" Name="Union City Transit" LastGenerated="11/26/2024 4:10:55 PM"/><GTFSAgency Id="VC" Name="Vacaville" LastGenerated="10/8/2025 10:28:20 AM"/><GTFSAgency Id="VN" Name="VINE Transit" LastGenerated="9/2/2025 2:03:27 PM"/><GTFSAgency Id="WC" Name="WestCat (Western Contra Costa)" LastGenerated="8/28/2025 3:28:59 AM"/><GTFSAgency Id="WH" Name="Livermore Amador Valley Transit Authority" LastGenerated="10/20/2025 1:57:17 PM"/></GTFSAgencies>